arglabels/__init__.py
arglabels-0.0.2.dist-info/LICENSE
arglabels-0.0.2.dist-info/METADATA
arglabels-0.0.2.dist-info/WHEEL
arglabels-0.0.2.dist-info/top_level.txt
arglabels-0.0.2.dist-info/RECORD
