Metadata-Version: 2.1
Name: arglabels
Version: 0.0.2
Summary: A simple decorator to enable Swift-like argument labels for functions.
Home-page: https://github.com/michael-harms/arglabels
Author: Michael Harms
Author-email: michaelharms95@icloud.com
License: UNKNOWN
Platform: UNKNOWN
Classifier: Programming Language :: Python :: 3
Classifier: License :: OSI Approved :: MIT License
Classifier: Operating System :: OS Independent
